{
  "id": "aashitagrawal/vanishing-gradient-problem-and-solution",
  "id_no": 40057103,
  "title": " \ud83d\ude36\u200d\ud83c\udf2b\ufe0f  vanishing gradient problem and solution",
  "code_file": "vanishing-gradient-problem-and-solution.ipynb",
  "language": "python",
  "kernel_type": "notebook",
  "is_private": false,
  "enable_gpu": false,
  "enable_tpu": false,
  "enable_internet": false,
  "keywords": [],
  "dataset_sources": [],
  "kernel_sources": [],
  "competition_sources": [],
  "model_sources": []
}